babble/__init__.py
portable/__init__.py
babble-2020.1.6.dist-info/METADATA
babble-2020.1.6.dist-info/WHEEL
babble-2020.1.6.dist-info/top_level.txt
babble-2020.1.6.dist-info/zip-safe
babble-2020.1.6.dist-info/RECORD
