Metadata-Version: 2.1
Name: babble
Version: 2020.1.6
Summary: Python library for parsing PDFs
Home-page: https://github.com/idin/babble
Author: Idin
Author-email: py@idin.ca
License: MIT
Keywords: PDF
Platform: UNKNOWN
Classifier: Development Status :: 3 - Alpha
Classifier: Intended Audience :: Developers
Classifier: Programming Language :: Python :: 3 :: Only
Classifier: Programming Language :: Python :: 3.6
Classifier: Programming Language :: Python :: 3.7
Classifier: Topic :: Software Development :: Libraries :: Python Modules
Requires-Python: ~=3.6
